{
  "name": "talker",
  "version": "0.1.0",
  "description": "Angular $log enhancer",
  "main": "./talker-0.1.0.min.js",
  "license": "MIT",
  "ignore": [
    "**/.*",
    "node_modules",
    "app/bower_components",
    "test",
    "config",
    "src",
    "scripts",
    ".*",
    "GruntFile.js"
  ],
  "devDependencies": {
    "angular": "*",
    "angular-mocks": "~1.2.1"
  },
  "homepage": "https://github.com/RobinBressan/talker",
  "_release": "0.1.0",
  "_resolution": {
    "type": "version",
    "tag": "0.1.0",
    "commit": "2f5d89d8572508adb342723a59b7f6f2a83a8bf4"
  },
  "_source": "git://github.com/RobinBressan/talker.git",
  "_target": "~0.1.0",
  "_originalSource": "talker",
  "_direct": true
}